darwin/__init__.py
darwin/__main__.py
darwin/cli.py
darwin/exceptions.py
python_darwin-0.0.1.dist-info/LICENSE
python_darwin-0.0.1.dist-info/METADATA
python_darwin-0.0.1.dist-info/WHEEL
python_darwin-0.0.1.dist-info/entry_points.txt
python_darwin-0.0.1.dist-info/top_level.txt
python_darwin-0.0.1.dist-info/RECORD
