Metadata-Version: 2.1
Name: python-darwin
Version: 0.0.1
Summary: Python package providing an API to Darwin, an online database for German Shepherds owned and maintained by the VDH.
Home-page: https://github.com/roaldnefs/python-darwin
Author: Roald Nefs
Author-email: info@roaldnefs.com
License: MIT
Platform: UNKNOWN
Classifier: Programming Language :: Python
Classifier: Programming Language :: Python :: 3
Classifier: Programming Language :: Python :: 3.6
Classifier: Programming Language :: Python :: 3.7
Classifier: Programming Language :: Python :: 3.8
Requires-Python: >=3.6.0
Requires-Dist: lxml (>=4.5.2)
Requires-Dist: requests (>=2.24.0)
